lilit/__init__.py
lilit/binning.py
lilit/experiments.yaml
lilit/functions.py
lilit/likelihood.py
lilit/planck_2018.ini
lilit/core/__init__.py
lilit/core/chi_square.py
lilit-1.3.0.dist-info/licenses/LICENSE
tests/__init__.py
tests/conftest.py
tests/test_approximations.py
tests/test_chi_square.py
tests/test_chi_square_simple.py
tests/test_lilit_likelihood.py
tests/test_mcmc.py
tests/data/cov.npy
tests/data/fiducial_cl.pkl
lilit-1.3.0.dist-info/METADATA
lilit-1.3.0.dist-info/WHEEL
lilit-1.3.0.dist-info/top_level.txt
lilit-1.3.0.dist-info/RECORD
