Metadata-Version: 2.4
Name: lilit
Version: 1.3.0
Summary: Likelihood for LiteBIRD
Author-email: Giacomo Galloni <giacomo.galloni@unife.it>
License: GNU General Public License v3.0
Project-URL: Homepage, https://github.com/ggalloni/LiLit/
Project-URL: Documentation, https://lilit.readthedocs.io/
Requires-Python: <3.14,>3.9
License-File: LICENSE
Requires-Dist: camb>=1.6.0
Requires-Dist: cobaya>=3.5.7
Requires-Dist: healpy>=1.17.3
Requires-Dist: matplotlib>=3.9.4
Requires-Dist: numpy>=2.0.2
Requires-Dist: pyyaml>=6.0.3
Provides-Extra: dev
Requires-Dist: pre-commit>=4.3.0; extra == "dev"
Requires-Dist: pytest>=8.4.2; extra == "dev"
Requires-Dist: pytest-cov>=7.0.0; extra == "dev"
Requires-Dist: ruff>=0.14.0; extra == "dev"
Requires-Dist: sphinx>=7.0.0; extra == "dev"
Requires-Dist: sphinx-rtd-theme>=2.0.0; extra == "dev"
Requires-Dist: sphinx-autodoc-typehints>=2.0.0; extra == "dev"
Dynamic: license-file
